trello_release_notes/__init__.py
trello_release_notes/__main__.py
trello_release_notes/trello_release_notes.py
trello_release_notes-0.2.5.dist-info/LICENSE
trello_release_notes-0.2.5.dist-info/METADATA
trello_release_notes-0.2.5.dist-info/WHEEL
trello_release_notes-0.2.5.dist-info/entry_points.txt
trello_release_notes-0.2.5.dist-info/top_level.txt
trello_release_notes-0.2.5.dist-info/RECORD
