Metadata-Version: 2.1
Name: trello-release-notes
Version: 0.2.5
Summary: Take your weekly done cards and turn them into a bulleted list in another column, just like Alice Goldfuss does.
Home-page: https://github.com/mattkatz/trello_release_notes
Author: Matt Katz
Author-email: github@morelightmorelight.com
License: MIT license
Keywords: trello_release_notes
Platform: UNKNOWN
Classifier: Development Status :: 2 - Pre-Alpha
Classifier: Intended Audience :: Developers
Classifier: License :: OSI Approved :: MIT License
Classifier: Natural Language :: English
Classifier: Programming Language :: Python :: 3
Classifier: Programming Language :: Python :: 3.6
Classifier: Programming Language :: Python :: 3.7
Requires-Dist: py-trello
Requires-Dist: ConfigArgParse
Requires-Dist: loguru
